{
  "title": "Apartament nr. 3, cu 3 camere - Parter",
  "description": "Apartament modern cu 3 camere la parter, cu terasa, ideal pentru familii. Construit în 2023 cu materiale de calitate superioară, pereți din cărămidă groasă pentru izolație fonică și termică excelentă. Acces rapid la București în 30 de minute cu trenul.",
  "price": 95000,
  "currency": "EUR",
  "status": "disponibil",
  "type": "apartament",
  "area": 90.3,
  "rooms": 3,
  "bedrooms": 2,
  "bathrooms": 1,
  "floor": 0,
  "totalFloors": 2,
  "parking": false,
  "garage": false,
  "balcony": false,
  "terrace": true,
  "garden": true,
  "yearBuilt": 2023,
  "mansarda": false,
  "images": [
    {
      "src": "/assets/img/property-1.jpg",
      "alt": "Apartament 3 camere parter - living"
    },
    {
      "src": "/assets/img/releveu-ap-3.jpg",
      "alt": "Apartament nr.3 - Gara Peris - 3 camere parter - Releveu"
    },
    {
      "src": "/assets/img/distribuire-ap-3.jpg",
      "alt": "Apartament nr.3 - Gara Peris - 3 camere parter - Distribuire"
    }
  ],
  "features": [
    "Izolație termică și fonică",
    "Pereți din cărămidă",
    "Faza construcție interioară la gri",
    "Geam termopan Salamander tripan",
    "Terasă privată",
    "Acces la curte comună",
    "Loc de parcare optional / neinclus in preț"
  ],
  "address": {
    "street": "Strada Gării",
    "city": "Peris",
    "county": "Ilfov"
  },
  "coordinates": {
    "lat": 44.677528,
    "lng": 25.997525
  },
  "featured": true,
  "order": 1,
  "roomSurfaces": [
    { "name": "Dormitor 1", "surface": 18.1 },
    { "name": "Dormitor 2", "surface": 15.6 },
    { "name": "Bucătărie", "surface": 8.5 },
    { "name": "Baie", "surface": 5.5 },
    { "name": "Living", "surface": 22.7 },
    { "name": "Terasă acoperită", "surface": 19.9 },
    { "name": "SUPRAFATA TOTALA", "surface": 90.3 }
  ]
}
